MANIFEST.in
setup.py
itc/__init__.py
itc.cli.egg-info/PKG-INFO
itc.cli.egg-info/SOURCES.txt
itc.cli.egg-info/dependency_links.txt
itc.cli.egg-info/not-zip-safe
itc.cli.egg-info/requires.txt
itc.cli.egg-info/top_level.txt
itc/bin/itc
itc/conf/__init__.py
itc/conf/conf.py
itc/core/__init__.py
itc/core/application.py
itc/core/colorer.py
itc/core/imageuploader.py
itc/core/inapp.py
itc/core/itccli.py
itc/core/review.py
itc/core/server.py
itc/parsers/__init__.py
itc/parsers/applicationparser.py
itc/parsers/baseparser.py
itc/parsers/inappparser.py
itc/parsers/serverparser.py
itc/util/__init__.py
itc/util/languages.json
itc/util/languages.py