Metadata-Version: 1.0
Name: itc.cli
Version: 0.4.5
Summary: iTunesConnect command line interface.
Home-page: https://github.com/kovpas/itc.cli
Author: Pavel Mazurin
Author-email: me@kovpas.ru
License: MIT
Platform: UNKNOWN
Classifier: Development Status :: 4 - Beta
Classifier: Intended Audience :: Developers
Classifier: License :: OSI Approved :: MIT License
Classifier: Operating System :: OS Independent
Classifier: Programming Language :: Python :: 2.7
